kuaizhan_zipkin
