Metadata-Version: 1.0
Name: kuaizhan-zipkin
Version: 0.8.2
Summary: kuaizhan zipkin sender
Home-page: UNKNOWN
Author: xuchen
Author-email: chenxu211618@sohu-inc.com
License: MIT License
Keywords: kuaizhan zipkin
Platform: any
